rdconfig/__init__.py
rdconfig/config.py
rdconfig/glb.py
rdconfig/global.py
rdconfig/private.py
rdconfig/protect.py
rdcrm/__init__.py
rdcrm/customer.py
rdcrm/login.py
rdcrm/product.py
rdcrm/salesOrder.py
rdcrm/bill/__init__.py
rdcrm/bill/salesOrder.py
rdcrm/md/__init__.py
rdcrm/md/customer.py
rdcrm/md/product.py
rdwebapi/__init__.py
rdwebapi/config.py
rdwebapi/glb.py
rdwebapi/private.py
rdwebapi/protect.py
rdwebapi-1.0.1.dist-info/LICENSE
rdwebapi-1.0.1.dist-info/METADATA
rdwebapi-1.0.1.dist-info/WHEEL
rdwebapi-1.0.1.dist-info/top_level.txt
rdwebapi-1.0.1.dist-info/RECORD
